{
  "required": true,
  "package": "com.example.mixin",
  "compatibilityLevel": "JAVA_21",
  "mixins": [
    "ExampleMixin"
  ],
  "injectors": {
    "defaultRequire": 1
  },
  "overwrites": {
    "requireAnnotations": true
  },
  "client": [
    "AbstractClientPlayerEntityMixin",
    "ChatMixin",
    "EntityRenderDispatcherMixin",
    "EntityRendererMixin",
    "GameMenuScreenMixin",
    "HandledScreenMixin",
    "InGameHudMixin",
    "ItemRendererMixin",
    "TitleScreenMixin",
    "WorldCaptureMixin"
  ]
}